LICENSE
LICENSE.fr
autoemailsmtp/__init__.py
autoemailsmtp/config.py
autoemailsmtp/notifiers/discord.py
autoemailsmtp/send_mail.py
autoemailsmtp-0.1.0.dist-info/LICENSE
autoemailsmtp-0.1.0.dist-info/LICENSE.fr
autoemailsmtp-0.1.0.dist-info/METADATA
autoemailsmtp-0.1.0.dist-info/WHEEL
autoemailsmtp-0.1.0.dist-info/RECORD
