Metadata-Version: 2.1
Name: autoemailsmtp
Version: 0.1.0
Summary: Send mail to SMTP
Home-page: https://github.com/M0NsTeRRR/AutoEmail
License: CeCILL
Keywords: email,smtp
Author: Ludovic Ortega
Author-email: ludovic.ortega@adminafk.fr
Requires-Python: >=3.8,<4.0
Classifier: License :: OSI Approved :: CEA CNRS Inria Logiciel Libre License, version 2.1 (CeCILL-2.1)
Classifier: License :: Other/Proprietary License
Classifier: Operating System :: OS Independent
Classifier: Programming Language :: Python
Classifier: Programming Language :: Python :: 3
Classifier: Programming Language :: Python :: 3.8
Classifier: Programming Language :: Python :: 3.9
Classifier: Programming Language :: Python :: 3.10
Classifier: Programming Language :: Python :: 3.11
Classifier: Programming Language :: Python :: 3.10
Classifier: Programming Language :: Python :: 3.11
Classifier: Programming Language :: Python :: 3.8
Classifier: Programming Language :: Python :: 3.9
Classifier: Topic :: Utilities
Requires-Dist: jinja2 (>=3.1.2,<4.0.0)
Requires-Dist: pydantic[dotenv] (>=1.10.6,<2.0.0)
Requires-Dist: requests (>=2.28.2,<3.0.0)
Project-URL: Repository, https://github.com/M0NsTeRRR/AutoEmail
